pydpd/__init__.py
pydpd/dpd.py
pydpd-0.1.4.12.dist-info/LICENSE
pydpd-0.1.4.12.dist-info/METADATA
pydpd-0.1.4.12.dist-info/WHEEL
pydpd-0.1.4.12.dist-info/top_level.txt
pydpd-0.1.4.12.dist-info/RECORD
