Metadata-Version: 2.1
Name: pydpd
Version: 0.1.4.12
Summary: DPD API Wrapper
Home-page: https://github.com/lewis-morris/pydpd
Author: Lewis Morris
Author-email: lewis.morris@gmail.com
License: MIT
Platform: UNKNOWN
